jac_vision/VERSION
jac_vision/__init__.py
jac_vision/detr/__init__.py
jac_vision/detr/detr.py
jac_vision/detr/model.py
jac_vision/detr/requirements.txt
jac_vision/dpt/__init__.py
jac_vision/dpt/dpt.py
jac_vision/dpt/model.py
jac_vision/dpt/requirements.txt
jac_vision/rftm/__init__.py
jac_vision/rftm/model.py
jac_vision/rftm/requirements.txt
jac_vision/rftm/rftm.py
jac_vision/yolos/__init__.py
jac_vision/yolos/model.py
jac_vision/yolos/requirements.txt
jac_vision/yolos/yolos.py
jac_vision-1.4.2.6.dist-info/METADATA
jac_vision-1.4.2.6.dist-info/WHEEL
jac_vision-1.4.2.6.dist-info/top_level.txt
jac_vision-1.4.2.6.dist-info/RECORD
