Metadata-Version: 2.1
Name: jac_vision
Version: 1.4.2.6
Home-page: https://github.com/Jaseci-Labs/jaseci
Author: Jason Mars
Author-email: jason@jaseci.org
Requires-Dist: jaseci ==1.4.2.6
Requires-Dist: pytest <7.1,>=7.0.1
Requires-Dist: pytest-order <1.1,>=1.0.1
Provides-Extra: all
Requires-Dist: torch <2.0.0,>=1.10.2 ; extra == 'all'
Requires-Dist: numpy >=1.23.0 ; extra == 'all'
Requires-Dist: transformers >=4.25.1 ; extra == 'all'
Requires-Dist: timm >=0.6.12 ; extra == 'all'
Provides-Extra: detr
Requires-Dist: transformers >=4.25.1 ; extra == 'detr'
Requires-Dist: torch <2.0.0,>=1.10.2 ; extra == 'detr'
Requires-Dist: timm >=0.6.12 ; extra == 'detr'
Provides-Extra: dpt
Requires-Dist: transformers >=4.25.1 ; extra == 'dpt'
Requires-Dist: torch <2.0.0,>=1.10.2 ; extra == 'dpt'
Provides-Extra: rftm
Requires-Dist: torch <2.0.0,>=1.10.2 ; extra == 'rftm'
Requires-Dist: numpy >=1.23.0 ; extra == 'rftm'
Provides-Extra: yolos
Requires-Dist: transformers >=4.25.1 ; extra == 'yolos'
Requires-Dist: torch <2.0.0,>=1.10.2 ; extra == 'yolos'
